dsa_utilities/__init__.py
dsa_utilities/timerfunc.py
dsa_utilities/queue/__init__.py
dsa_utilities/queue/queue.py
dsa_utilities/stacks/__init__.py
dsa_utilities/stacks/balanced_parantheses.py
dsa_utilities/stacks/stack.py
dsa_utilities-0.9.dist-info/METADATA
dsa_utilities-0.9.dist-info/WHEEL
dsa_utilities-0.9.dist-info/top_level.txt
dsa_utilities-0.9.dist-info/RECORD
