Metadata-Version: 2.1
Name: dsa-utilities
Version: 0.9
Summary: Utilities functions for DSA
Home-page: https://github.com/theonlynischal/dsa_utils_package
Author: Nischal Lal Shrestha
Author-email: aakrist666@gmail.com
License: UNKNOWN
Platform: UNKNOWN
